{"is_source_file": false, "format": "", "description": "", "external_files": [], "external_methods": [], "published": [], "classes": [], "methods": [], "calls": [], "search-terms": [], "state": 2, "file_id": 3, "knowledge_revision": 30, "git_revision": "2698f70d94fe76d14b083c0f96b87e08bb918df0", "hash": "fd066e8a8a18d39fdab3ee0f9eac4ca3", "format-version": 4, "code-base-name": "tic_tac_toe_frontend", "filename": "tic_tac_toe_frontend/README.md", "revision_history": [{"30": "2698f70d94fe76d14b083c0f96b87e08bb918df0"}]}